setup.py
physics/__init__.py
physics/__main__.py
physics/graph.py
physics/physics.py
physics/rocket.py
rosshill_physics.egg-info/PKG-INFO
rosshill_physics.egg-info/SOURCES.txt
rosshill_physics.egg-info/dependency_links.txt
rosshill_physics.egg-info/entry_points.txt
rosshill_physics.egg-info/requires.txt
rosshill_physics.egg-info/top_level.txt