Metadata-Version: 1.0
Name: rosshill-physics
Version: 0.23
Summary: Python command line rocket simulator.
Home-page: http://www.rosshill.ca
Author: Ross Hill
Author-email: rosshill@protonmail.com
License: UNKNOWN
Platform: UNKNOWN
